{
    "configurations": [
        {
            "name": "Mac",
            "includePath": [
                "/Applications/Arduino.app/Contents/Java/tools/**",
                "/Applications/Arduino.app/Contents/Java/hardware/arduino/avr/**",
                "${workspaceFolder}/**"
            ],
            "browse": {
                "limitSymbolsToIncludedHeaders": false,
                "path": [
                    "/Users/joshrandall/Documents/Arduino/libraries"
                ]
            },
            "defines": [],
            "macFrameworkPath": [
                "/Applications/Xcode-beta.app/Contents/Developer/Platforms/MacOSX.platform/Developer/SDKs/MacOSX10.11.sdk/System/Library/Frameworks"
            ],
            "compilerPath": "/usr/bin/clang",
            "cStandard": "c11",
            "cppStandard": "c++17",
            "intelliSenseMode": "clang-x64",
            "forcedInclude": [
                "/Applications/Arduino.app/Contents/Java/hardware/arduino/avr/cores/arduino/Arduino.h"
            ]
        }
    ],
    "version": 4
}